calldules.py
calldules-1.0.dist-info/METADATA
calldules-1.0.dist-info/DESCRIPTION.rst
calldules-1.0.dist-info/WHEEL
calldules-1.0.dist-info/RECORD
calldules-1.0.dist-info/pydist.json
calldules-1.0.dist-info/zip-safe
calldules-1.0.dist-info/top_level.txt
