Metadata-Version: 2.0
Name: calldules
Version: 1.0
Summary: making modules callable, for not very good reasons.
Home-page: https://github.com/Ivoz/calldules/
Author: Matthew Iversen
Author-email: matt@notevencode.com
License: MIT
Platform: UNKNOWN
Classifier: Development Status :: 4 - Beta
Classifier: License :: OSI Approved :: MIT License
Classifier: Programming Language :: Python :: 2
Classifier: Programming Language :: Python :: 3
Classifier: Programming Language :: Python :: Implementation :: CPython
Classifier: Operating System :: OS Independent
Classifier: Intended Audience :: Developers
Classifier: Topic :: Utilities
